.gitignore
MANIFEST.in
README.rst
setup.py
collective/__init__.py
collective.check_munin.egg-info/PKG-INFO
collective.check_munin.egg-info/SOURCES.txt
collective.check_munin.egg-info/dependency_links.txt
collective.check_munin.egg-info/entry_points.txt
collective.check_munin.egg-info/namespace_packages.txt
collective.check_munin.egg-info/not-zip-safe
collective.check_munin.egg-info/requires.txt
collective.check_munin.egg-info/top_level.txt
collective/check_munin/__init__.py
collective/check_munin/check_munin.py
docs/HISTORY.txt
docs/LICENSE.txt