Metadata-Version: 1.1
Name: collective.check-munin
Version: 1.0
Summary: Nagios plugin to check munin via rrd
Home-page: https://github.com/smcmahon/collective.check_munin
Author: Steve McMahon
Author-email: steve@dcn.org
License: GPL
Platform: UNKNOWN
Classifier: Programming Language :: Python
Classifier: Topic :: System :: Systems Administration
Classifier: Topic :: System :: Monitoring
Classifier: Intended Audience :: System Administrators
Classifier: Environment :: Plugins
Classifier: Development Status :: 5 - Production/Stable
